README.txt
pindex.py
setup.py
pindex.egg-info/PKG-INFO
pindex.egg-info/SOURCES.txt
pindex.egg-info/dependency_links.txt
pindex.egg-info/top_level.txt
pindex.egg-info/zip-safe