Metadata-Version: 1.1
Name: pindex
Version: 0.5.1
Summary: An awesome tool for indexing matrices. propose a new concept “single index” (as in matlab) to index the elements from matrices. exchange python-style index(begin with 0) with matlab-style index(begin with 1)
Home-page: https://github.com/Freakwill/pindex
Author: William Song
Author-email: songcwzjut@163.com
License: MIT
Keywords: Index,Matrix,Single Index,Style of Index
Platform: UNKNOWN
Classifier: License :: Public Domain
Classifier: Programming Language :: Python
Classifier: Programming Language :: Python :: 3.6
Classifier: Intended Audience :: Science/Research
Classifier: Operating System :: OS Independent
Classifier: Topic :: Scientific/Engineering :: Mathematics
Classifier: Natural Language :: English
